dqueue/__init__.py
dqueue/exceptions.py
dqueue/item.py
dqueue/queues/__init__.py
dqueue/queues/base.py
dqueue/queues/memory.py
dqueue/queues/rabbitmq.py
dqueue/queues/redis.py
dqueue/runners.py
dqueue/storages/__init__.py
dqueue/storages/base.py
dqueue/storages/memory.py
dqueue/storages/redis.py
dqueue/utils.py
dqueue-0.1.2.dist-info/WHEEL
dqueue-0.1.2.dist-info/METADATA
dqueue-0.1.2.dist-info/RECORD
